pwmdist/__init__.py
pwmdist/gpdplots.py
pwmdist/gpdpwmFit.py
pwmdist-0.0.1.dist-info/LICENSE
pwmdist-0.0.1.dist-info/METADATA
pwmdist-0.0.1.dist-info/WHEEL
pwmdist-0.0.1.dist-info/top_level.txt
pwmdist-0.0.1.dist-info/RECORD
